Metadata-Version: 2.4
Name: wecom-bot-mcp-server-remotefile
Version: 0.12.1
Summary: WeCom Bot MCP Server - A Python server for WeCom (WeChat Work) bot following the Model Context Protocol (MCP)
License-File: LICENSE
Author: longhao
Author-email: hal.long@outlook.com
Requires-Python: >=3.10,<4.0
Classifier: License :: OSI Approved :: MIT License
Classifier: Operating System :: OS Independent
Classifier: Programming Language :: Python :: 3
Classifier: Programming Language :: Python :: 3.10
Classifier: Programming Language :: Python :: 3.11
Classifier: Programming Language :: Python :: 3.12
Classifier: Programming Language :: Python :: 3.13
Classifier: Programming Language :: Python :: 3.14
Requires-Dist: aiohttp (>=3.11.13)
Requires-Dist: ftfy (>=6.3.1)
Requires-Dist: httpx (>=0.28.1)
Requires-Dist: loguru (>=0.7.3)
Requires-Dist: mcp (>=1.3.0)
Requires-Dist: notify-bridge (>=0.6.1)
Requires-Dist: pillow (>=10.2.0)
Requires-Dist: platformdirs (>=4.2.0)
Requires-Dist: pydantic (>=2.6.1)
Requires-Dist: tenacity (>=9.0.0)
